panversion/__init__.py
panversion-0.1.0.dist-info/LICENSE
panversion-0.1.0.dist-info/METADATA
panversion-0.1.0.dist-info/WHEEL
panversion-0.1.0.dist-info/top_level.txt
panversion-0.1.0.dist-info/RECORD
